{"name":"Node.fwends","tagline":"A mini version of the popular site Fwend.me in Node form.","body":"### Node.fwends\r\n\r\nA simple Node.js with a few extra features to emphasize knowledge of WebScoket technologies. Leverages the Express framework to provide a fully expressed chat-service including\r\n\r\n* Ability to chat real-time with an unlimited number of users.\r\n* Aliasing to allow for users to go by a specific name.\r\n* A feature that notifies all chat participants if another user is typing.","google":"","note":"Don't delete this file! It's used internally to help with page regeneration."}